checkout_page_sdk/__init__.py
checkout_page_sdk/callback.py
checkout_page_sdk/checkout_page.py
checkout_page_sdk/gate.py
checkout_page_sdk/payment.py
checkout_page_sdk/process_exception.py
checkout_page_sdk/signature_handler.py
1d3_checkout_sdk-1.0.1.dist-info/LICENSE
1d3_checkout_sdk-1.0.1.dist-info/METADATA
1d3_checkout_sdk-1.0.1.dist-info/WHEEL
1d3_checkout_sdk-1.0.1.dist-info/top_level.txt
1d3_checkout_sdk-1.0.1.dist-info/RECORD
